README.rst
setup.cfg
setup.py
humblebundle/__init__.py
humblebundle/client.py
humblebundle/decorators.py
humblebundle/exceptions.py
humblebundle/handlers.py
humblebundle/models.py
humblebundle.egg-info/PKG-INFO
humblebundle.egg-info/SOURCES.txt
humblebundle.egg-info/dependency_links.txt
humblebundle.egg-info/requires.txt
humblebundle.egg-info/top_level.txt