Metadata-Version: 1.1
Name: humblebundle
Version: 0.1.1
Summary: Humble Indie Bundle API client
Home-page: https://github.com/saik0/humblebundle-python
Author: Joel Pedraza
Author-email: joel@joelpedraza.com
License: UNKNOWN
Download-URL: https://github.com/saik0/humblebundle-python/tarball/0.1.1
Platform: UNKNOWN
